tests/__init__.py
tests/test_html.py
tests/test_parse.py
tests/test_utils.py
usfm_utils/__init__.py
usfm_utils/elements/__init__.py
usfm_utils/elements/abstract_elements.py
usfm_utils/elements/document.py
usfm_utils/elements/element_impls.py
usfm_utils/elements/element_visitor.py
usfm_utils/elements/footnote_utils.py
usfm_utils/elements/paragraph_utils.py
usfm_utils/render_html/__init__.py
usfm_utils/render_html/html_utils.py
usfm_utils/render_html/html_visitor.py
usfm_utils/usfm/__init__.py
usfm_utils/usfm/escape_text.py
usfm_utils/usfm/flags.py
usfm_utils/usfm/lex.py
usfm_utils/usfm/lex_utils.py
usfm_utils/usfm/parse.py
usfm_utils/usfm/parsetab.py
usfm_utils/usfm/tokens.py
usfm_utils-1.0.0.dist-info/DESCRIPTION.rst
usfm_utils-1.0.0.dist-info/METADATA
usfm_utils-1.0.0.dist-info/RECORD
usfm_utils-1.0.0.dist-info/WHEEL
usfm_utils-1.0.0.dist-info/metadata.json
usfm_utils-1.0.0.dist-info/top_level.txt
